{
  "config": {
    "hw_platform": [
      "MTP", "Dragon", "Surf", "ELISH"
    ],
    "soc_id": [
      "291", "246", "305", "321", "339", "356"
    ]
  },
  "sar_algo": {
    "owner": "sar_algo",
    ".params":{
      "owner": "sar_algo",
        "threshold1": {
          "ver": "3", "type": "flt", "data": "50"
        },
        "threshold2": {
          "ver": "5", "type": "flt", "data": "250"
        },
        "threshold3": {
          "ver": "5", "type": "flt", "data": "250"
        },
        "threshold4": {
          "ver": "5", "type": "flt", "data": "250"
        },
        "threshold5": {
          "ver": "5", "type": "flt", "data": "250"
        },
        "use_acc_gyro": {
          "ver": "2", "type": "flt", "data": "0"
        },
        "use_qmi": {
          "ver": "2", "type": "flt", "data": "0"
        }
    },
    ".params_reg2":{
      "owner": "sar_algo",
        "threshold1": {
          "ver": "2", "type": "flt", "data": "3000"
        },
        "threshold2": {
          "ver": "2", "type": "flt", "data": "600"
        },
        "threshold3": {
          "ver": "2", "type": "flt", "data": "1500"
        },
        "threshold4": {
          "ver": "2", "type": "flt", "data": "500"
        }
    }
  }
}